paraclient/__init__.py
paraclient/auth.py
paraclient/constraint.py
paraclient/pager.py
paraclient/paraclient.py
paraclient/paraobject.py
paraclient/version.py
paraclient-1.37.0.dist-info/licenses/LICENSE
paraclient-1.37.0.dist-info/WHEEL
paraclient-1.37.0.dist-info/METADATA
paraclient-1.37.0.dist-info/RECORD
