Metadata-Version: 2.4
Name: paraclient
Version: 1.37.0
Summary: Python client for Para
Author: Alexander Bogdanovski
Author-email: Alexander Bogdanovski <alex@erudika.com>
License-Expression: Apache-2.0
License-File: LICENSE
Classifier: Programming Language :: Python
Classifier: Programming Language :: Python :: 3
Classifier: Programming Language :: Python :: 3 :: Only
Classifier: Programming Language :: Python :: Implementation :: CPython
Requires-Dist: requests>=2.32.5
Requires-Dist: aws-requests-auth==0.4.3
Requires-Dist: urllib3>=2.6.2
Requires-Dist: testcontainers>=4.6.0 ; extra == 'test'
Requires-Python: >=3.9
Project-URL: Documentation, https://paraio.org/docs
Project-URL: Homepage, https://github.com/Erudika/para-client-python
Project-URL: Issues, https://github.com/Erudika/para-client-python/issues
Provides-Extra: test
